LICENSE.txt
MANIFEST.in
README.rst
requirements.core.txt
requirements.txt
setup.py
core_cache_manager_app/__init__.py
core_cache_manager_app/settings.py
core_cache_manager_app.egg-info/PKG-INFO
core_cache_manager_app.egg-info/SOURCES.txt
core_cache_manager_app.egg-info/dependency_links.txt
core_cache_manager_app.egg-info/requires.txt
core_cache_manager_app.egg-info/top_level.txt
core_cache_manager_app/components/__init__.py
core_cache_manager_app/components/data_cached/__init__.py
core_cache_manager_app/components/data_cached/api.py
core_cache_manager_app/components/data_cached/models.py
core_cache_manager_app/views/__init__.py
core_cache_manager_app/views/admin/__init__.py
core_cache_manager_app/views/admin/forms.py
tests/__init__.py
tests/test_settings.py