Metadata-Version: 2.1
Name: core-cache-manager-app
Version: 1.3.0
Summary: Cache management functionalities
Home-page: https://github.com/usnistgov/core_cache_manager_app
Author: NIST EL/ITL Lab
Author-email: itl_inquiries@nist.gov
License: UNKNOWN
Platform: UNKNOWN
License-File: LICENSE.txt
